ylecomments/__init__.py
ylecomments/ylecomments.py
ylecomments-1.0.1.dist-info/LICENSE.txt
ylecomments-1.0.1.dist-info/METADATA
ylecomments-1.0.1.dist-info/WHEEL
ylecomments-1.0.1.dist-info/top_level.txt
ylecomments-1.0.1.dist-info/RECORD
