Metadata-Version: 2.1
Name: ylecomments
Version: 1.0.1
Summary: A Python wrapper for Yle's Comments API
Home-page: https://github.com/juhanias/ylecomments
Author: Juhani Astikainen
Author-email: juhani.astikainen@gmail.com
License: MIT
Project-URL: Bug Tracker, https://github.com/juhanias/ylecomments/issues
Classifier: Programming Language :: Python :: 3
Classifier: License :: OSI Approved :: MIT License
Classifier: Operating System :: OS Independent
Classifier: Topic :: Software Development :: Libraries
Classifier: Topic :: Software Development :: Libraries :: Python Modules
Classifier: Programming Language :: Python :: 3.7
Requires-Python: >=3.7
License-File: LICENSE.txt
Requires-Dist: requests (<=2.28.2)
